cremerlab/__init__.py
cremerlab/bayes.py
cremerlab/growth.py
cremerlab/hplc.py
cremerlab_utils-0.0.3.dist-info/METADATA
cremerlab_utils-0.0.3.dist-info/WHEEL
cremerlab_utils-0.0.3.dist-info/top_level.txt
cremerlab_utils-0.0.3.dist-info/RECORD
