Metadata-Version: 2.1
Name: cremerlab-utils
Version: 0.0.3
Summary: Python utilities for members of the Jonas Cremer lab at Stanford University
Home-page: https://github.com/cremerlab/cremerlab-utils
Author: Griffin Chure
Author-email: griffinchure@gmail.com
License: MIT
Platform: UNKNOWN
Classifier: Development Status :: 1 - Planning
Classifier: Intended Audience :: Developers
Classifier: Programming Language :: Python :: 3
